l2m4m.py
L2M4M-1.0.4.dist-info/LICENSE
L2M4M-1.0.4.dist-info/METADATA
L2M4M-1.0.4.dist-info/WHEEL
L2M4M-1.0.4.dist-info/top_level.txt
L2M4M-1.0.4.dist-info/RECORD
