Metadata-Version: 2.1
Name: L2M4M
Version: 1.0.4
Summary: Extends Markdown to convert LaTeX to MathML.
Author-email: "M. P. van de Weerd" <michael@parcifal.dev>
License: LICENCE
Project-URL: Homepage, https://gitlab.com/parcifal/l2m4m
Project-URL: Bug Tracker, https://gitlab.com/parcifal/l2m4m/-/issues
Keywords: markdown,latex,mathml
Classifier: Development Status :: 5 - Production/Stable
Classifier: Intended Audience :: Developers
Classifier: License :: OSI Approved :: GNU General Public License v3 (GPLv3)
License-File: LICENSE
Requires-Dist: markdown
Requires-Dist: latex2mathml
